<?xml version="1.0" encoding="UTF-8"?>
<con:soapui-project id="bb24775a-8b79-4a89-94e6-d0a343b4f1af" activeEnvironment="Default" name="IT21-2018-Komosar-Aleksa" resourceRoot="" soapui-version="5.6.0" abortOnError="false" runType="SEQUENTIAL" xmlns:con="http://eviware.com/soapui/config"><con:settings/><con:interface xsi:type="con:RestService" id="337bfdfc-a2a9-4db7-82b3-6e74dfe7f5f7" wadlVersion="http://wadl.dev.java.net/2009/02" name="http://localhost:8083" type="rest" xmlns:xsi="http://www.w3.org/2001/XMLSchema-instance"><con:settings/><con:definitionCache type="TEXT" rootPart=""/><con:endpoints><con:endpoint>http://localhost:8083</con:endpoint></con:endpoints><con:resource name="Projekat Get All" path="/projekat" id="100e8655-0953-46f5-8d58-6a58646ec03a"><con:settings/><con:parameters/><con:method name="Method Get All" id="e06596e7-b0fa-4255-ae0f-7549752c7f14" method="GET"><con:settings/><con:parameters/><con:representation type="RESPONSE"><con:mediaType>application/json</con:mediaType><con:status>200</con:status><con:params/><con:element>Response</con:element></con:representation><con:representation type="FAULT"><con:mediaType>application/json</con:mediaType><con:status>400</con:status><con:params/><con:element xmlns:proj="http://localhost/projekat">proj:Fault</con:element></con:representation><con:representation type="RESPONSE"><con:mediaType xsi:nil="true"/><con:status>0</con:status><con:params/><con:element>data</con:element></con:representation><con:request name="Projekat Get All" id="4c16f969-387c-4860-b7bb-cd174af638b8" mediaType="application/json" postQueryString="false"><con:settings><con:setting id="com.eviware.soapui.impl.wsdl.WsdlRequest@request-headers">&lt;xml-fragment/></con:setting></con:settings><con:endpoint>http://localhost:8083</con:endpoint><con:request/><con:originalUri>http://localhost/projekat</con:originalUri><con:credentials><con:authType>No Authorization</con:authType></con:credentials><con:jmsConfig JMSDeliveryMode="PERSISTENT"/><con:jmsPropertyConfig/><con:parameters/></con:request></con:method></con:resource><con:resource name="Projekat Get by ID" path="/projekat/{id}" id="cb1ed90d-d387-4233-b30a-94e05a1c343b"><con:settings/><con:parameters><con:parameter><con:name>id</con:name><con:value>2</con:value><con:style>TEMPLATE</con:style><con:default>2</con:default></con:parameter></con:parameters><con:method name="Method Get by ID" id="4f89f2f8-e78c-4566-9c6b-82b1b9bd88e8" method="GET"><con:settings/><con:parameters/><con:representation type="RESPONSE"><con:mediaType>application/json</con:mediaType><con:status>200</con:status><con:params/><con:element>Response</con:element></con:representation><con:request name="Projekat Get by ID" id="b4e72bd2-6f09-4860-bbd0-5471e3fc2ee3" mediaType="application/json"><con:settings><con:setting id="com.eviware.soapui.impl.wsdl.WsdlRequest@request-headers">&lt;xml-fragment/></con:setting></con:settings><con:endpoint>http://localhost:8083</con:endpoint><con:request/><con:originalUri>http://localhost/projekat/</con:originalUri><con:credentials><con:authType>No Authorization</con:authType></con:credentials><con:jmsConfig JMSDeliveryMode="PERSISTENT"/><con:jmsPropertyConfig/><con:parameters><entry key="id" value="-100" xmlns="http://eviware.com/soapui/config"/></con:parameters><con:parameterOrder><con:entry>id</con:entry></con:parameterOrder></con:request></con:method></con:resource><con:resource name="Projekat Get by Naziv" path="/projekatNaziv/{naziv}" id="2cf2b2cc-2556-4273-82b8-963fb3976845"><con:settings/><con:parameters><con:parameter><con:name>naziv</con:name><con:value>naziv</con:value><con:style>TEMPLATE</con:style><con:default>naziv</con:default></con:parameter></con:parameters><con:method name="Method Get by Naziv" id="428d7984-dca8-4d89-919c-ca22521bf5f6" method="GET"><con:settings/><con:parameters/><con:representation type="RESPONSE"><con:mediaType>application/json</con:mediaType><con:status>200</con:status><con:params/><con:element>Response</con:element></con:representation><con:request name="Projekat Get by Naziv" id="b1786c74-3686-4708-aae5-af83612c6b7c" mediaType="application/json"><con:settings><con:setting id="com.eviware.soapui.impl.wsdl.WsdlRequest@request-headers">&lt;xml-fragment/></con:setting></con:settings><con:endpoint>http://localhost:8083</con:endpoint><con:request/><con:originalUri>http://localhost/projekatNaziv/naziv</con:originalUri><con:credentials><con:authType>No Authorization</con:authType></con:credentials><con:jmsConfig JMSDeliveryMode="PERSISTENT"/><con:jmsPropertyConfig/><con:parameters><entry key="naziv" value="mobi" xmlns="http://eviware.com/soapui/config"/></con:parameters></con:request></con:method></con:resource><con:resource name="Projekat Insert" path="/projekat" id="59d2e48b-9cd1-4755-a54b-002ea1a09a75"><con:settings/><con:parameters/><con:method name="Method Insert" id="cbed2d28-b44c-4585-8ad7-a7e0050fe367" method="POST"><con:settings/><con:parameters/><con:representation type="FAULT"><con:mediaType>application/json</con:mediaType><con:status>500</con:status><con:params/><con:element xmlns:proj="http://localhost/projekat">proj:Fault</con:element></con:representation><con:representation type="REQUEST"><con:mediaType>application/json</con:mediaType><con:params/></con:representation><con:representation type="RESPONSE"><con:mediaType xsi:nil="true"/><con:status>200</con:status><con:params/><con:element>data</con:element></con:representation><con:representation type="RESPONSE"><con:mediaType xsi:nil="true"/><con:status>200</con:status><con:params/><con:element>data</con:element></con:representation><con:representation type="RESPONSE"><con:mediaType xsi:nil="true"/><con:status>200</con:status><con:params/><con:element>data</con:element></con:representation><con:representation type="RESPONSE"><con:mediaType xsi:nil="true"/><con:status>200</con:status><con:params/><con:element>data</con:element></con:representation><con:request name="Projekat Insert" id="37e5a2fe-bab2-46b6-9e31-b165a0aef57d" mediaType="application/json" postQueryString="false"><con:settings><con:setting id="com.eviware.soapui.impl.wsdl.WsdlRequest@request-headers">&lt;xml-fragment/></con:setting></con:settings><con:endpoint>http://localhost:8083</con:endpoint><con:request>{
      "id": -56,
      "naziv": "RVA - Studentska sluzba",
      "opis": "Opis tehnologija..",
      "oznaka": "RVA"
}</con:request><con:originalUri>http://localhost/projekat</con:originalUri><con:credentials><con:authType>No Authorization</con:authType></con:credentials><con:jmsConfig JMSDeliveryMode="PERSISTENT"/><con:jmsPropertyConfig/><con:parameters/></con:request></con:method></con:resource><con:resource name="Projekat Update" path="/projekat" id="e0ea2b40-a40b-4af0-a01a-4d411d19038a"><con:settings/><con:parameters/><con:method name="Method Update" id="5275e1f8-24ff-450e-84fa-e33f34fb5e90" method="PUT"><con:settings/><con:parameters/><con:representation type="REQUEST"><con:mediaType>application/json</con:mediaType><con:params/></con:representation><con:representation type="RESPONSE"><con:mediaType xsi:nil="true"/><con:status>200</con:status><con:params/><con:element>data</con:element></con:representation><con:representation type="RESPONSE"><con:mediaType xsi:nil="true"/><con:status>200</con:status><con:params/><con:element>data</con:element></con:representation><con:representation type="RESPONSE"><con:mediaType xsi:nil="true"/><con:status>200</con:status><con:params/><con:element>data</con:element></con:representation><con:request name="Projekat Update" id="62034367-3707-42ad-9f59-2de14923040d" mediaType="application/json" postQueryString="false"><con:settings><con:setting id="com.eviware.soapui.impl.wsdl.WsdlRequest@request-headers">&lt;xml-fragment/></con:setting></con:settings><con:endpoint>http://localhost:8083</con:endpoint><con:request>      {
      "id": -46,
      "naziv": "RVAUpdate - Studentska sluzba",
      "opis": "Opis tehnologija..",
      "oznaka": "RVA2"
   }</con:request><con:originalUri>http://localhost/projekat</con:originalUri><con:credentials><con:authType>No Authorization</con:authType></con:credentials><con:jmsConfig JMSDeliveryMode="PERSISTENT"/><con:jmsPropertyConfig/><con:parameters/></con:request></con:method></con:resource><con:resource name="Projekat Delete" path="/projekat/{id}" id="1cd4147f-28cf-46f9-8e7a-4bed235694bf"><con:settings/><con:parameters><con:parameter><con:name>id</con:name><con:value>-46</con:value><con:style>TEMPLATE</con:style><con:default>-46</con:default></con:parameter></con:parameters><con:method name="Method Delete" id="893743c2-9888-48a7-9c23-b09efa035389" method="DELETE"><con:settings/><con:parameters/><con:representation type="REQUEST"><con:mediaType>application/json</con:mediaType><con:params/></con:representation><con:representation type="RESPONSE"><con:mediaType xsi:nil="true"/><con:status>200</con:status><con:params/><con:element>data</con:element></con:representation><con:representation type="RESPONSE"><con:mediaType xsi:nil="true"/><con:status>204</con:status><con:params/><con:element>data</con:element></con:representation><con:representation type="RESPONSE"><con:mediaType xsi:nil="true"/><con:status>204</con:status><con:params/><con:element>data</con:element></con:representation><con:representation type="RESPONSE"><con:mediaType xsi:nil="true"/><con:status>204</con:status><con:params/><con:element>data</con:element></con:representation><con:representation type="RESPONSE"><con:mediaType xsi:nil="true"/><con:status>204</con:status><con:params/><con:element>data</con:element></con:representation><con:representation type="RESPONSE"><con:mediaType xsi:nil="true"/><con:status>204</con:status><con:params/><con:element>data</con:element></con:representation><con:representation type="RESPONSE"><con:mediaType xsi:nil="true"/><con:status>204</con:status><con:params/><con:element>data</con:element></con:representation><con:representation type="RESPONSE"><con:mediaType xsi:nil="true"/><con:status>204</con:status><con:params/><con:element>data</con:element></con:representation><con:representation type="RESPONSE"><con:mediaType xsi:nil="true"/><con:status>204</con:status><con:params/><con:element>data</con:element></con:representation><con:representation type="RESPONSE"><con:mediaType xsi:nil="true"/><con:status>204</con:status><con:params/><con:element>data</con:element></con:representation><con:representation type="RESPONSE"><con:mediaType xsi:nil="true"/><con:status>204</con:status><con:params/><con:element>data</con:element></con:representation><con:representation type="FAULT"><con:mediaType>application/json</con:mediaType><con:status>500</con:status><con:params/><con:element xmlns:ns="http://localhost/projekat/-46">ns:Fault</con:element></con:representation><con:representation type="RESPONSE"><con:mediaType>application/json</con:mediaType><con:status>200</con:status><con:params/><con:element xmlns:ns="http://localhost/projekat/-46">ns:Response</con:element></con:representation><con:representation type="RESPONSE"><con:mediaType xsi:nil="true"/><con:status>200</con:status><con:params/><con:element>data</con:element></con:representation><con:request name="Projekat Delete" id="eb8e2262-a671-4e89-addb-48d6614acf14" mediaType="application/json" postQueryString="false"><con:settings><con:setting id="com.eviware.soapui.impl.wsdl.WsdlRequest@request-headers">&lt;xml-fragment/></con:setting></con:settings><con:endpoint>http://localhost:8083</con:endpoint><con:request/><con:originalUri>http://localhost/projekat/-46</con:originalUri><con:credentials><con:authType>No Authorization</con:authType></con:credentials><con:jmsConfig JMSDeliveryMode="PERSISTENT"/><con:jmsPropertyConfig/><con:parameters><entry key="id" value="-100" xmlns="http://eviware.com/soapui/config"/></con:parameters><con:parameterOrder><con:entry>id</con:entry></con:parameterOrder></con:request></con:method></con:resource><con:resource name="Smer Get All" path="/smer" id="ed9729fd-0daa-4235-9060-de376dbb00dd"><con:settings/><con:parameters/><con:method name="Method Get All" id="8e6e6e82-e914-4c9b-9570-3c447a3354bf" method="GET"><con:settings/><con:parameters/><con:representation type="RESPONSE"><con:mediaType>application/json</con:mediaType><con:status>200</con:status><con:params/><con:element>Response</con:element></con:representation><con:representation type="RESPONSE"><con:mediaType xsi:nil="true"/><con:status>0</con:status><con:params/><con:element>data</con:element></con:representation><con:representation type="RESPONSE"><con:mediaType xsi:nil="true"/><con:status>0</con:status><con:params/><con:element>data</con:element></con:representation><con:representation type="RESPONSE"><con:mediaType xsi:nil="true"/><con:status>0</con:status><con:params/><con:element>data</con:element></con:representation><con:request name="Smer Get All" id="fa044d17-0122-402e-ab59-66f504a0c3e7" mediaType="application/json"><con:settings><con:setting id="com.eviware.soapui.impl.wsdl.WsdlRequest@request-headers">&lt;xml-fragment/></con:setting></con:settings><con:endpoint>http://localhost:8083</con:endpoint><con:request/><con:originalUri>http://localhost/smer</con:originalUri><con:credentials><con:authType>No Authorization</con:authType></con:credentials><con:jmsConfig JMSDeliveryMode="PERSISTENT"/><con:jmsPropertyConfig/><con:parameters/></con:request></con:method></con:resource><con:resource name="Smer Get by ID" path="/smer/{id}" id="37a466d5-4232-43f0-85eb-6584fbee5202"><con:settings/><con:parameters><con:parameter><con:name>id</con:name><con:value>4</con:value><con:style>TEMPLATE</con:style><con:default>4</con:default></con:parameter></con:parameters><con:method name="Method Get by ID" id="a5ae2803-35ad-4461-87bd-8f796cbe2dbd" method="GET"><con:settings/><con:parameters/><con:representation type="RESPONSE"><con:mediaType>application/json</con:mediaType><con:status>200</con:status><con:params/><con:element>Response</con:element></con:representation><con:request name="Smer Get by ID" id="92eedc3d-9945-45da-8cb2-a1eae14708b8" mediaType="application/json"><con:settings><con:setting id="com.eviware.soapui.impl.wsdl.WsdlRequest@request-headers">&lt;xml-fragment/></con:setting></con:settings><con:endpoint>http://localhost:8083</con:endpoint><con:request/><con:originalUri>http://localhost/smer/</con:originalUri><con:credentials><con:authType>No Authorization</con:authType></con:credentials><con:jmsConfig JMSDeliveryMode="PERSISTENT"/><con:jmsPropertyConfig/><con:parameters><entry key="id" value="1" xmlns="http://eviware.com/soapui/config"/></con:parameters><con:parameterOrder><con:entry>id</con:entry></con:parameterOrder></con:request></con:method></con:resource><con:resource name="Smer Get by Naziv" path="/smerNaziv/{naziv}" id="3c4c166b-8e24-450a-a498-42a3b7918102"><con:settings/><con:parameters><con:parameter><con:name>naziv</con:name><con:value>infor</con:value><con:style>TEMPLATE</con:style><con:default>infor</con:default></con:parameter></con:parameters><con:method name="Method Get by Naziv" id="e7374983-dda7-42c4-9efd-577fd869bcf9" method="GET"><con:settings/><con:parameters/><con:representation type="RESPONSE"><con:mediaType>application/json</con:mediaType><con:status>200</con:status><con:params/><con:element>Response</con:element></con:representation><con:representation type="FAULT"><con:mediaType>application/json</con:mediaType><con:status>400</con:status><con:params/><con:element xmlns:smer="http://localhost/smer/">smer:Fault</con:element></con:representation><con:request name="Smer Get by Naziv" id="566a2042-bb0d-4efb-96de-99fd86d081e8" mediaType="application/json"><con:settings><con:setting id="com.eviware.soapui.impl.wsdl.WsdlRequest@request-headers">&lt;xml-fragment/></con:setting></con:settings><con:endpoint>http://localhost:8083</con:endpoint><con:request/><con:originalUri>http://localhost/smer/</con:originalUri><con:credentials><con:authType>No Authorization</con:authType></con:credentials><con:jmsConfig JMSDeliveryMode="PERSISTENT"/><con:jmsPropertyConfig/><con:parameters><entry key="naziv" value="i" xmlns="http://eviware.com/soapui/config"/></con:parameters><con:parameterOrder><con:entry>naziv</con:entry></con:parameterOrder></con:request></con:method></con:resource><con:resource name="Smer Insert" path="/smer" id="f48a1df1-9503-4804-99cd-3c79ed0508b8"><con:settings/><con:parameters/><con:method name="Method Insert" id="092dcfc1-304c-4d4a-a696-357d035d5b4b" method="POST"><con:settings/><con:parameters/><con:representation type="REQUEST"><con:mediaType>application/json</con:mediaType><con:params/></con:representation><con:representation type="FAULT"><con:mediaType>application/json</con:mediaType><con:status>500</con:status><con:params/><con:element xmlns:smer="http://localhost/smer">smer:Fault</con:element></con:representation><con:representation type="RESPONSE"><con:mediaType xsi:nil="true"/><con:status>200</con:status><con:params/><con:element>data</con:element></con:representation><con:representation type="RESPONSE"><con:mediaType xsi:nil="true"/><con:status>200</con:status><con:params/><con:element>data</con:element></con:representation><con:representation type="RESPONSE"><con:mediaType xsi:nil="true"/><con:status>200</con:status><con:params/><con:element>data</con:element></con:representation><con:representation type="RESPONSE"><con:mediaType xsi:nil="true"/><con:status>200</con:status><con:params/><con:element>data</con:element></con:representation><con:request name="Smer Insert" id="f8a934cb-fccd-4a53-9a7e-99f40a4b4c2a" mediaType="application/json" postQueryString="false"><con:settings><con:setting id="com.eviware.soapui.impl.wsdl.WsdlRequest@request-headers">&lt;xml-fragment/></con:setting></con:settings><con:endpoint>http://localhost:8083</con:endpoint><con:request>      {
      "id": -55,
      "naziv": "Novo Inzenjerstvo informacionih sistema",
      "oznaka": "Novo IT"
   }</con:request><con:originalUri>http://localhost/smer</con:originalUri><con:credentials><con:authType>No Authorization</con:authType></con:credentials><con:jmsConfig JMSDeliveryMode="PERSISTENT"/><con:jmsPropertyConfig/><con:parameters/></con:request></con:method></con:resource><con:resource name="Smer Update" path="/smer" id="24b0d7fc-6113-40a0-945e-8560ee13b832"><con:settings/><con:parameters/><con:method name="Method Update" id="b1f0ae3b-3c32-4eee-b35c-5e1f895e74ea" method="PUT"><con:settings/><con:parameters/><con:representation type="REQUEST"><con:mediaType>application/json</con:mediaType><con:params/></con:representation><con:representation type="FAULT"><con:mediaType xsi:nil="true"/><con:status>409</con:status><con:params/><con:element>data</con:element></con:representation><con:representation type="FAULT"><con:mediaType xsi:nil="true"/><con:status>409</con:status><con:params/><con:element>data</con:element></con:representation><con:representation type="RESPONSE"><con:mediaType xsi:nil="true"/><con:status>200</con:status><con:params/><con:element>data</con:element></con:representation><con:representation type="RESPONSE"><con:mediaType xsi:nil="true"/><con:status>200</con:status><con:params/><con:element>data</con:element></con:representation><con:representation type="RESPONSE"><con:mediaType xsi:nil="true"/><con:status>200</con:status><con:params/><con:element>data</con:element></con:representation><con:request name="Smer Update" id="7d5ddbc0-b31b-4d14-af46-d09aae2fdc2f" mediaType="application/json" postQueryString="false"><con:settings><con:setting id="com.eviware.soapui.impl.wsdl.WsdlRequest@request-headers">&lt;xml-fragment/></con:setting></con:settings><con:endpoint>http://localhost:8083</con:endpoint><con:request>      {
      "id": -100,
      "naziv": "UpdateNovo Inzenjerstvo informacionih sistema",
      "oznaka": "Update Novo IT"
   }</con:request><con:originalUri>http://localhost/smer</con:originalUri><con:credentials><con:authType>No Authorization</con:authType></con:credentials><con:jmsConfig JMSDeliveryMode="PERSISTENT"/><con:jmsPropertyConfig/><con:parameters/></con:request></con:method></con:resource><con:resource name="Smer Delete" path="/smer/{id}" id="133af278-8cf3-43d1-803b-5023b81df6e9"><con:settings/><con:parameters><con:parameter><con:name>id</con:name><con:style>TEMPLATE</con:style></con:parameter></con:parameters><con:method name="Method Delete" id="ec1cefac-01e2-4a21-8dc5-ae19ffc6907f" method="DELETE"><con:settings/><con:parameters/><con:representation type="REQUEST"><con:mediaType>application/json</con:mediaType><con:params/></con:representation><con:representation type="RESPONSE"><con:mediaType xsi:nil="true"/><con:status>200</con:status><con:params/><con:element>data</con:element></con:representation><con:representation type="RESPONSE"><con:mediaType xsi:nil="true"/><con:status>200</con:status><con:params/><con:element>data</con:element></con:representation><con:representation type="RESPONSE"><con:mediaType xsi:nil="true"/><con:status>200</con:status><con:params/><con:element>data</con:element></con:representation><con:representation type="RESPONSE"><con:mediaType xsi:nil="true"/><con:status>200</con:status><con:params/><con:element>data</con:element></con:representation><con:representation type="RESPONSE"><con:mediaType xsi:nil="true"/><con:status>200</con:status><con:params/><con:element>data</con:element></con:representation><con:request name="Smer Delete" id="36c3e142-8246-4f96-8e85-2125ed3241e4" mediaType="application/json" postQueryString="false"><con:settings><con:setting id="com.eviware.soapui.impl.wsdl.WsdlRequest@request-headers">&lt;xml-fragment/></con:setting></con:settings><con:endpoint>http://localhost:8083</con:endpoint><con:request/><con:originalUri>http://localhost/smer/-100</con:originalUri><con:credentials><con:authType>No Authorization</con:authType></con:credentials><con:jmsConfig JMSDeliveryMode="PERSISTENT"/><con:jmsPropertyConfig/><con:parameters><entry key="id" value="-100" xmlns="http://eviware.com/soapui/config"/></con:parameters><con:parameterOrder><con:entry>id</con:entry></con:parameterOrder></con:request></con:method></con:resource><con:resource name="Grupa Get All" path="/grupa" id="fb8f7fdb-7d50-4d38-a3ed-cf624caaf944"><con:settings/><con:parameters><con:parameter><con:name>id</con:name><con:value>-100</con:value><con:style>TEMPLATE</con:style><con:default>-100</con:default></con:parameter></con:parameters><con:method name="Method Get All" id="73f0a8cc-f7b6-4c73-9285-963d7bdbaa5e" method="GET"><con:settings/><con:parameters/><con:representation type="FAULT"><con:mediaType>application/json</con:mediaType><con:status>404</con:status><con:params/><con:element xmlns:grup="http://localhost/grupa">grup:Fault</con:element></con:representation><con:representation type="RESPONSE"><con:mediaType>application/json</con:mediaType><con:status>200</con:status><con:params/><con:element>Response</con:element></con:representation><con:representation type="REQUEST"><con:mediaType>application/json</con:mediaType><con:params/></con:representation><con:representation type="RESPONSE"><con:mediaType xsi:nil="true"/><con:status>200</con:status><con:params/><con:element>data</con:element></con:representation><con:representation type="RESPONSE"><con:mediaType xsi:nil="true"/><con:status>200</con:status><con:params/><con:element>data</con:element></con:representation><con:request name="Grupa Get All" id="d3272ab3-3aa7-4bbf-a8c5-863d6d78423e" mediaType="application/json" postQueryString="false"><con:settings><con:setting id="com.eviware.soapui.impl.wsdl.WsdlRequest@request-headers">&lt;xml-fragment/></con:setting></con:settings><con:endpoint>http://localhost:8083</con:endpoint><con:request/><con:originalUri>http://localhost/grupa</con:originalUri><con:credentials><con:authType>No Authorization</con:authType></con:credentials><con:jmsConfig JMSDeliveryMode="PERSISTENT"/><con:jmsPropertyConfig/><con:parameters><entry key="id" value="" xmlns="http://eviware.com/soapui/config"/></con:parameters><con:parameterOrder><con:entry>id</con:entry></con:parameterOrder></con:request></con:method></con:resource><con:resource name="Grupa Get By ID" path="/grupa/{id}" id="ccfaca49-f8d9-44d1-b82c-4311c0a82f94"><con:settings/><con:parameters><con:parameter><con:name>id</con:name><con:value>1</con:value><con:style>TEMPLATE</con:style><con:default>1</con:default></con:parameter></con:parameters><con:method name="Method Get By ID" id="4a914f3c-e93a-4307-a19f-a97b43e936f2" method="GET"><con:settings/><con:parameters/><con:representation type="RESPONSE"><con:mediaType>application/json</con:mediaType><con:status>200</con:status><con:params/><con:element xmlns:ns="http://localhost/grupa/1">ns:Response</con:element></con:representation><con:request name="Grupa Get By ID" id="a5a03c45-09b1-4d4b-81f5-69a4d71b8c9a" mediaType="application/json"><con:settings><con:setting id="com.eviware.soapui.impl.wsdl.WsdlRequest@request-headers">&lt;xml-fragment/></con:setting></con:settings><con:endpoint>http://localhost:8083</con:endpoint><con:request/><con:originalUri>http://localhost/grupa/1</con:originalUri><con:credentials><con:authType>No Authorization</con:authType></con:credentials><con:jmsConfig JMSDeliveryMode="PERSISTENT"/><con:jmsPropertyConfig/><con:parameters><entry key="id" value="-100" xmlns="http://eviware.com/soapui/config"/></con:parameters><con:parameterOrder><con:entry>id</con:entry></con:parameterOrder></con:request></con:method></con:resource><con:resource name="Grupa Get By Oznaka" path="/grupaOznaka/{oznaka}" id="b9cf305d-147c-4513-8f2a-090b88220860"><con:settings/><con:parameters><con:parameter><con:name>oznaka</con:name><con:value>m</con:value><con:style>TEMPLATE</con:style><con:default>m</con:default></con:parameter></con:parameters><con:method name="Method Get By Oznaka" id="ca2450ec-1e7e-4b81-8255-827c98c9b2f7" method="GET"><con:settings/><con:parameters/><con:representation type="RESPONSE"><con:mediaType>application/json</con:mediaType><con:status>200</con:status><con:params/><con:element>Response</con:element></con:representation><con:request name="Grupa Get By Oznaka" id="3a8212ff-0839-4e71-80d4-ce7017fc63cc" mediaType="application/json"><con:settings><con:setting id="com.eviware.soapui.impl.wsdl.WsdlRequest@request-headers">&lt;xml-fragment/></con:setting></con:settings><con:endpoint>http://localhost:8083</con:endpoint><con:request/><con:originalUri>http://localhost/grupaOznaka/m</con:originalUri><con:credentials><con:authType>No Authorization</con:authType></con:credentials><con:jmsConfig JMSDeliveryMode="PERSISTENT"/><con:jmsPropertyConfig/><con:parameters><entry key="oznaka" value="III" xmlns="http://eviware.com/soapui/config"/></con:parameters><con:parameterOrder><con:entry>oznaka</con:entry></con:parameterOrder></con:request></con:method></con:resource><con:resource name="Grupa Insert" path="/grupa" id="dad60cfa-15eb-453f-99ee-702a5c3bc52a"><con:settings/><con:parameters/><con:method name="Method Insert" id="9e553531-62af-456e-b2d5-6031fe9c37ac" method="POST"><con:settings/><con:parameters/><con:representation type="REQUEST"><con:mediaType>application/json</con:mediaType><con:params/></con:representation><con:representation type="FAULT"><con:mediaType>application/json</con:mediaType><con:status>400 500</con:status><con:params/><con:element xmlns:grup="http://localhost/grupa">grup:Fault</con:element></con:representation><con:representation type="RESPONSE"><con:mediaType xsi:nil="true"/><con:status>200</con:status><con:params/><con:element>data</con:element></con:representation><con:representation type="RESPONSE"><con:mediaType xsi:nil="true"/><con:status>200</con:status><con:params/><con:element>data</con:element></con:representation><con:representation type="RESPONSE"><con:mediaType xsi:nil="true"/><con:status>200</con:status><con:params/><con:element>data</con:element></con:representation><con:request name="Grupa Insert" id="acc80a41-6ccc-4763-88f0-a8fc65f49182" mediaType="application/json" postQueryString="false"><con:settings><con:setting id="com.eviware.soapui.impl.wsdl.WsdlRequest@request-headers">&lt;xml-fragment/></con:setting></con:settings><con:endpoint>http://localhost:8083</con:endpoint><con:request>      {
      "id": 33,
      "oznaka": "V",
      "smer":       {
         "id": 5,
         "naziv": "Inzenjerski menadzment",
         "oznaka": "IM"
      }
      }</con:request><con:originalUri>http://localhost/grupa</con:originalUri><con:credentials><con:authType>No Authorization</con:authType></con:credentials><con:jmsConfig JMSDeliveryMode="PERSISTENT"/><con:jmsPropertyConfig/><con:parameters/></con:request></con:method></con:resource><con:resource name="Grupa Update" path="/grupa" id="36708e51-9760-49ab-8bdf-26a655e07bc1"><con:settings/><con:parameters/><con:method name="Method Update" id="e710ea86-80a9-479b-9aab-1498a563d2f8" method="PUT"><con:settings/><con:parameters/><con:representation type="REQUEST"><con:mediaType>application/json</con:mediaType><con:params/></con:representation><con:representation type="FAULT"><con:mediaType>application/json</con:mediaType><con:status>400</con:status><con:params/><con:element xmlns:grup="http://localhost/grupa">grup:Fault</con:element></con:representation><con:representation type="RESPONSE"><con:mediaType xsi:nil="true"/><con:status>200</con:status><con:params/><con:element>data</con:element></con:representation><con:representation type="RESPONSE"><con:mediaType xsi:nil="true"/><con:status>200</con:status><con:params/><con:element>data</con:element></con:representation><con:representation type="RESPONSE"><con:mediaType xsi:nil="true"/><con:status>200</con:status><con:params/><con:element>data</con:element></con:representation><con:request name="Grupa Update" id="59abd9d1-d851-4822-b6b7-a7a33d4275b9" mediaType="application/json" postQueryString="false"><con:settings><con:setting id="com.eviware.soapui.impl.wsdl.WsdlRequest@request-headers">&lt;xml-fragment/></con:setting></con:settings><con:endpoint>http://localhost:8083</con:endpoint><con:request>      {
      "id": -100,
      "oznaka": "II",
      "smer":       {
         "id": 2
      }
      }</con:request><con:originalUri>http://localhost/grupa</con:originalUri><con:credentials><con:authType>No Authorization</con:authType></con:credentials><con:jmsConfig JMSDeliveryMode="PERSISTENT"/><con:jmsPropertyConfig/><con:parameters/></con:request></con:method></con:resource><con:resource name="Grupa Delete" path="/grupa/{id}" id="ae42e849-693a-4686-8484-f36d8379c0d7"><con:settings/><con:parameters><con:parameter><con:name>id</con:name><con:value>-100</con:value><con:style>TEMPLATE</con:style><con:default>-100</con:default></con:parameter></con:parameters><con:method name="Method Delete" id="0fb68d24-f0e0-4363-b5f3-0c9ce9fedbcb" method="DELETE"><con:settings/><con:parameters/><con:representation type="RESPONSE"><con:mediaType>application/json</con:mediaType><con:status>200</con:status><con:params/><con:element>Response</con:element></con:representation><con:representation type="REQUEST"><con:mediaType>application/json</con:mediaType><con:params/></con:representation><con:representation type="RESPONSE"><con:mediaType xsi:nil="true"/><con:status>200</con:status><con:params/><con:element>data</con:element></con:representation><con:representation type="RESPONSE"><con:mediaType xsi:nil="true"/><con:status>200</con:status><con:params/><con:element>data</con:element></con:representation><con:representation type="RESPONSE"><con:mediaType xsi:nil="true"/><con:status>200</con:status><con:params/><con:element>data</con:element></con:representation><con:representation type="RESPONSE"><con:mediaType xsi:nil="true"/><con:status>200</con:status><con:params/><con:element>data</con:element></con:representation><con:request name="Grupa Delete" id="1f528f93-3e33-4e92-aff8-b4f56c9ff629" mediaType="application/json" postQueryString="false"><con:settings><con:setting id="com.eviware.soapui.impl.wsdl.WsdlRequest@request-headers">&lt;xml-fragment/></con:setting></con:settings><con:endpoint>http://localhost:8083</con:endpoint><con:request/><con:originalUri>http://localhost/grupa/</con:originalUri><con:credentials><con:authType>No Authorization</con:authType></con:credentials><con:jmsConfig JMSDeliveryMode="PERSISTENT"/><con:jmsPropertyConfig/><con:parameters><entry key="id" value="-100" xmlns="http://eviware.com/soapui/config"/></con:parameters><con:parameterOrder><con:entry>id</con:entry></con:parameterOrder></con:request></con:method></con:resource><con:resource name="Student Get All" path="/student" id="7f18818b-8c35-4f02-af46-ffbddc8964eb"><con:settings/><con:parameters/><con:method name="Method Get All" id="04b80002-ce45-4e06-8d85-fda74e1a1bcf" method="GET"><con:settings/><con:parameters/><con:representation type="RESPONSE"><con:mediaType xsi:nil="true"/><con:status>0</con:status><con:params/><con:element>data</con:element></con:representation><con:representation type="RESPONSE"><con:mediaType xsi:nil="true"/><con:status>0</con:status><con:params/><con:element>data</con:element></con:representation><con:representation type="RESPONSE"><con:mediaType xsi:nil="true"/><con:status>0</con:status><con:params/><con:element>data</con:element></con:representation><con:representation type="RESPONSE"><con:mediaType xsi:nil="true"/><con:status>0</con:status><con:params/><con:element>data</con:element></con:representation><con:representation type="RESPONSE"><con:mediaType xsi:nil="true"/><con:status>0</con:status><con:params/><con:element>data</con:element></con:representation><con:representation type="RESPONSE"><con:mediaType xsi:nil="true"/><con:status>0</con:status><con:params/><con:element>data</con:element></con:representation><con:representation type="RESPONSE"><con:mediaType>application/json</con:mediaType><con:status>200</con:status><con:params/><con:element>Response</con:element></con:representation><con:request name="Student Get All" id="8dea8085-26d6-40dd-a3b4-2c6d9ed47c7f" mediaType="application/json"><con:settings><con:setting id="com.eviware.soapui.impl.wsdl.WsdlRequest@request-headers">&lt;xml-fragment/></con:setting></con:settings><con:endpoint>http://localhost:8083</con:endpoint><con:request/><con:originalUri>http://localhost/student</con:originalUri><con:credentials><con:authType>No Authorization</con:authType></con:credentials><con:jmsConfig JMSDeliveryMode="PERSISTENT"/><con:jmsPropertyConfig/><con:parameters/></con:request></con:method></con:resource><con:resource name="Student Get By ID" path="/student/{id}" id="ede161bd-bed4-439c-bc5b-da844351762d"><con:settings/><con:parameters><con:parameter><con:name>id</con:name><con:value>1</con:value><con:style>TEMPLATE</con:style><con:default>1</con:default></con:parameter></con:parameters><con:method name="Method Get By ID" id="abd81993-8e09-4204-834a-e3a81c55f683" method="GET"><con:settings/><con:parameters/><con:representation type="RESPONSE"><con:mediaType>application/json</con:mediaType><con:status>200</con:status><con:params/><con:element>Response</con:element></con:representation><con:representation type="FAULT"><con:mediaType>application/json</con:mediaType><con:status>500</con:status><con:params/><con:element xmlns:stud="http://localhost/student/">stud:Fault</con:element></con:representation><con:request name="Student Get By ID" id="112a7476-782d-4132-9dea-190da243e466" mediaType="application/json"><con:settings><con:setting id="com.eviware.soapui.impl.wsdl.WsdlRequest@request-headers">&lt;xml-fragment/></con:setting></con:settings><con:endpoint>http://localhost:8083</con:endpoint><con:request/><con:originalUri>http://localhost/student/</con:originalUri><con:credentials><con:authType>No Authorization</con:authType></con:credentials><con:jmsConfig JMSDeliveryMode="PERSISTENT"/><con:jmsPropertyConfig/><con:parameters/><con:parameterOrder><con:entry>id</con:entry></con:parameterOrder></con:request></con:method></con:resource><con:resource name="Student Get By Grupa" path="/studentGrupaID/{id}" id="48ef0c32-b6f3-4ff1-8deb-eafbb8fb27b9"><con:settings/><con:parameters><con:parameter><con:name>id</con:name><con:value>1</con:value><con:style>TEMPLATE</con:style><con:default>1</con:default></con:parameter></con:parameters><con:method name="Method Get By Grupa" id="124ce21e-b489-42b3-a05c-983611f350db" method="GET"><con:settings/><con:parameters/><con:representation type="FAULT"><con:mediaType>application/json</con:mediaType><con:status>404</con:status><con:params/><con:element xmlns:stud="http://localhost/studentGrupaID/">stud:Fault</con:element></con:representation><con:representation type="RESPONSE"><con:mediaType>application/json</con:mediaType><con:status>200</con:status><con:params/><con:element>Response</con:element></con:representation><con:request name="Student Get By Grupa" id="8ce25536-f768-4037-ab41-fb5e4a7710bc" mediaType="application/json"><con:settings><con:setting id="com.eviware.soapui.impl.wsdl.WsdlRequest@request-headers">&lt;xml-fragment/></con:setting></con:settings><con:endpoint>http://localhost:8083</con:endpoint><con:request/><con:originalUri>http://localhost/studentGrupaID/</con:originalUri><con:credentials><con:authType>No Authorization</con:authType></con:credentials><con:jmsConfig JMSDeliveryMode="PERSISTENT"/><con:jmsPropertyConfig/><con:parameters><entry key="id" value="1" xmlns="http://eviware.com/soapui/config"/></con:parameters><con:parameterOrder><con:entry>id</con:entry></con:parameterOrder></con:request></con:method></con:resource><con:resource name="Student Get By ID Less" path="/studentPoId/{id}" id="7df4cb30-9632-4f68-b815-950f1d38228b"><con:settings/><con:parameters><con:parameter><con:name>id</con:name><con:value>5</con:value><con:style>TEMPLATE</con:style><con:default>5</con:default></con:parameter></con:parameters><con:method name="Method Get By ID Less" id="aab93823-b4e5-42db-afe9-346c55737d7f" method="GET"><con:settings/><con:parameters/><con:representation type="RESPONSE"><con:mediaType>application/json</con:mediaType><con:status>200</con:status><con:params/><con:element>Response</con:element></con:representation><con:request name="Student Get By ID Less" id="1aa7ebad-51e2-492a-8c4b-5b16714fa776" mediaType="application/json"><con:settings><con:setting id="com.eviware.soapui.impl.wsdl.WsdlRequest@request-headers">&lt;xml-fragment/></con:setting></con:settings><con:endpoint>http://localhost:8083</con:endpoint><con:request/><con:originalUri>http://localhost/studentBrIndeksa/5</con:originalUri><con:credentials><con:authType>No Authorization</con:authType></con:credentials><con:jmsConfig JMSDeliveryMode="PERSISTENT"/><con:jmsPropertyConfig/><con:parameters><entry key="id" value="2" xmlns="http://eviware.com/soapui/config"/></con:parameters><con:parameterOrder><con:entry>id</con:entry></con:parameterOrder></con:request></con:method></con:resource><con:resource name="Student Insert" path="/student" id="bc3b1f67-8098-45ed-8f3a-fcc8c9ed3f2b"><con:settings/><con:parameters/><con:method name="Method Insert" id="bbe9b5e2-50f8-4983-887d-801018dbe045" method="POST"><con:settings/><con:parameters/><con:representation type="REQUEST"><con:mediaType>application/json</con:mediaType><con:params/></con:representation><con:representation type="FAULT"><con:mediaType>application/json</con:mediaType><con:status>400 500</con:status><con:params/><con:element xmlns:stud="http://localhost/student">stud:Fault</con:element></con:representation><con:representation type="RESPONSE"><con:mediaType xsi:nil="true"/><con:status>200</con:status><con:params/><con:element>data</con:element></con:representation><con:representation type="RESPONSE"><con:mediaType xsi:nil="true"/><con:status>200</con:status><con:params/><con:element>data</con:element></con:representation><con:representation type="RESPONSE"><con:mediaType xsi:nil="true"/><con:status>200</con:status><con:params/><con:element>data</con:element></con:representation><con:representation type="RESPONSE"><con:mediaType xsi:nil="true"/><con:status>200</con:status><con:params/><con:element>data</con:element></con:representation><con:representation type="RESPONSE"><con:mediaType xsi:nil="true"/><con:status>200</con:status><con:params/><con:element>data</con:element></con:representation><con:representation type="RESPONSE"><con:mediaType xsi:nil="true"/><con:status>200</con:status><con:params/><con:element>data</con:element></con:representation><con:representation type="RESPONSE"><con:mediaType xsi:nil="true"/><con:status>200</con:status><con:params/><con:element>data</con:element></con:representation><con:representation type="RESPONSE"><con:mediaType xsi:nil="true"/><con:status>200</con:status><con:params/><con:element>data</con:element></con:representation><con:request name="Student Insert" id="3af35aa9-2853-49f5-8f4a-888f857b7f19" mediaType="application/json" postQueryString="false"><con:settings><con:setting id="com.eviware.soapui.impl.wsdl.WsdlRequest@request-headers">&lt;xml-fragment/></con:setting></con:settings><con:endpoint>http://localhost:8083</con:endpoint><con:request>{
   "id": -100,
   "brojIndeksa": "AAATest21/2018",
   "ime": "TestAleksa",
   "prezime": "TestKomosar",
   "grupa":    {
      "id": 1,
      "oznaka": "II",
      "smer":       {
         "id": 1,
         "naziv": "AAInzenjerstvo informacionih sistema",
         "oznaka": "IT"
      }
   },
   "projekat":    {
      "id": 4,
      "naziv": "AAANaucna konferencija",
      "opis": "Kreiranje baze podata IS Naucne konferencije FTN-a. Pored razumevanja procesa organizovanja dogadja, potrebno je izraditi semu cele baze podataka, ogranicenja, kao i relacionu semu BP.",
      "oznaka": "PBP"
   }
}</con:request><con:originalUri>http://localhost/student</con:originalUri><con:credentials><con:authType>No Authorization</con:authType></con:credentials><con:jmsConfig JMSDeliveryMode="PERSISTENT"/><con:jmsPropertyConfig/><con:parameters/></con:request></con:method></con:resource><con:resource name="Student Update" path="/student" id="2a576e2b-e98b-4bbb-8bf3-434bc8c6bbb3"><con:settings/><con:parameters/><con:method name="Method Update" id="9138c107-a1ff-422e-964c-d166d606d0c6" method="PUT"><con:settings/><con:parameters/><con:representation type="REQUEST"><con:mediaType>application/json</con:mediaType><con:params/></con:representation><con:representation type="RESPONSE"><con:mediaType xsi:nil="true"/><con:status>200</con:status><con:params/><con:element>data</con:element></con:representation><con:representation type="RESPONSE"><con:mediaType xsi:nil="true"/><con:status>200</con:status><con:params/><con:element>data</con:element></con:representation><con:representation type="RESPONSE"><con:mediaType xsi:nil="true"/><con:status>204</con:status><con:params/><con:element>data</con:element></con:representation><con:representation type="RESPONSE"><con:mediaType xsi:nil="true"/><con:status>200</con:status><con:params/><con:element>data</con:element></con:representation><con:representation type="RESPONSE"><con:mediaType xsi:nil="true"/><con:status>200</con:status><con:params/><con:element>data</con:element></con:representation><con:representation type="RESPONSE"><con:mediaType xsi:nil="true"/><con:status>200</con:status><con:params/><con:element>data</con:element></con:representation><con:representation type="RESPONSE"><con:mediaType xsi:nil="true"/><con:status>204</con:status><con:params/><con:element>data</con:element></con:representation><con:representation type="RESPONSE"><con:mediaType xsi:nil="true"/><con:status>204</con:status><con:params/><con:element>data</con:element></con:representation><con:representation type="RESPONSE"><con:mediaType xsi:nil="true"/><con:status>204</con:status><con:params/><con:element>data</con:element></con:representation><con:representation type="RESPONSE"><con:mediaType xsi:nil="true"/><con:status>200</con:status><con:params/><con:element>data</con:element></con:representation><con:request name="Student Update" id="f3c966bb-36a7-46e0-aa52-259ec90400f5" mediaType="application/json" postQueryString="false"><con:settings><con:setting id="com.eviware.soapui.impl.wsdl.WsdlRequest@request-headers">&lt;xml-fragment/></con:setting></con:settings><con:endpoint>http://localhost:8083</con:endpoint><con:request>{
   "id": -100,
   "brojIndeksa": "IzmenaAAATest21/2018",
   "ime": "TestAleksa",
   "prezime": "TestKomosar",
   "grupa":    {
      "id": 1,
      "oznaka": "II",
      "smer":       {
         "id": 1,
         "naziv": "Inzenjerstvo informacionih sistema",
         "oznaka": "IT"
      }
   },
   "projekat":    {
      "id": 4,
      "naziv": "Naucna konferencija",
      "opis": "Kreiranje baze podata IS Naucne konferencije FTN-a. Pored razumevanja procesa organizovanja dogadja, potrebno je izraditi semu cele baze podataka, ogranicenja, kao i relacionu semu BP.",
      "oznaka": "PBP"
   }
}</con:request><con:originalUri>http://localhost/student</con:originalUri><con:credentials><con:authType>No Authorization</con:authType></con:credentials><con:jmsConfig JMSDeliveryMode="PERSISTENT"/><con:jmsPropertyConfig/><con:parameters/></con:request></con:method></con:resource><con:resource name="Student Delete" path="/student/{id}" id="80c3cde3-0581-4971-a113-a89b1de9e11b"><con:settings/><con:parameters><con:parameter><con:name>id</con:name><con:style>TEMPLATE</con:style></con:parameter></con:parameters><con:method name="Method Delete" id="4d5434cc-ec45-4a7a-8c76-0809a0123183" method="DELETE"><con:settings/><con:parameters/><con:representation type="RESPONSE"><con:mediaType>application/json</con:mediaType><con:status>200</con:status><con:params/><con:element xmlns:ns="http://localhost/student/8">ns:Response</con:element></con:representation><con:representation type="RESPONSE"><con:mediaType xsi:nil="true"/><con:status>200</con:status><con:params/><con:element>data</con:element></con:representation><con:representation type="REQUEST"><con:mediaType>application/json</con:mediaType><con:params/></con:representation><con:representation type="RESPONSE"><con:mediaType xsi:nil="true"/><con:status>204</con:status><con:params/><con:element>data</con:element></con:representation><con:representation type="FAULT"><con:mediaType>application/json</con:mediaType><con:status>500</con:status><con:params/><con:element xmlns:ns="http://localhost/student/8">ns:Fault</con:element></con:representation><con:representation type="RESPONSE"><con:mediaType xsi:nil="true"/><con:status>204</con:status><con:params/><con:element>data</con:element></con:representation><con:representation type="RESPONSE"><con:mediaType xsi:nil="true"/><con:status>204</con:status><con:params/><con:element>data</con:element></con:representation><con:representation type="RESPONSE"><con:mediaType xsi:nil="true"/><con:status>204</con:status><con:params/><con:element>data</con:element></con:representation><con:representation type="RESPONSE"><con:mediaType xsi:nil="true"/><con:status>204</con:status><con:params/><con:element>data</con:element></con:representation><con:representation type="RESPONSE"><con:mediaType xsi:nil="true"/><con:status>204</con:status><con:params/><con:element>data</con:element></con:representation><con:representation type="RESPONSE"><con:mediaType xsi:nil="true"/><con:status>200</con:status><con:params/><con:element>data</con:element></con:representation><con:representation type="RESPONSE"><con:mediaType xsi:nil="true"/><con:status>204</con:status><con:params/><con:element>data</con:element></con:representation><con:representation type="RESPONSE"><con:mediaType xsi:nil="true"/><con:status>204</con:status><con:params/><con:element>data</con:element></con:representation><con:representation type="RESPONSE"><con:mediaType xsi:nil="true"/><con:status>204</con:status><con:params/><con:element>data</con:element></con:representation><con:representation type="RESPONSE"><con:mediaType xsi:nil="true"/><con:status>204</con:status><con:params/><con:element>data</con:element></con:representation><con:representation type="RESPONSE"><con:mediaType xsi:nil="true"/><con:status>204</con:status><con:params/><con:element>data</con:element></con:representation><con:representation type="RESPONSE"><con:mediaType xsi:nil="true"/><con:status>204</con:status><con:params/><con:element>data</con:element></con:representation><con:representation type="RESPONSE"><con:mediaType xsi:nil="true"/><con:status>200</con:status><con:params/><con:element>data</con:element></con:representation><con:representation type="RESPONSE"><con:mediaType xsi:nil="true"/><con:status>204</con:status><con:params/><con:element>data</con:element></con:representation><con:representation type="RESPONSE"><con:mediaType xsi:nil="true"/><con:status>204</con:status><con:params/><con:element>data</con:element></con:representation><con:representation type="RESPONSE"><con:mediaType xsi:nil="true"/><con:status>200</con:status><con:params/><con:element>data</con:element></con:representation><con:representation type="RESPONSE"><con:mediaType xsi:nil="true"/><con:status>204</con:status><con:params/><con:element>data</con:element></con:representation><con:representation type="RESPONSE"><con:mediaType xsi:nil="true"/><con:status>204</con:status><con:params/><con:element>data</con:element></con:representation><con:representation type="RESPONSE"><con:mediaType xsi:nil="true"/><con:status>204</con:status><con:params/><con:element>data</con:element></con:representation><con:representation type="RESPONSE"><con:mediaType xsi:nil="true"/><con:status>204</con:status><con:params/><con:element>data</con:element></con:representation><con:representation type="RESPONSE"><con:mediaType xsi:nil="true"/><con:status>204</con:status><con:params/><con:element>data</con:element></con:representation><con:representation type="RESPONSE"><con:mediaType xsi:nil="true"/><con:status>204</con:status><con:params/><con:element>data</con:element></con:representation><con:representation type="RESPONSE"><con:mediaType xsi:nil="true"/><con:status>204</con:status><con:params/><con:element>data</con:element></con:representation><con:representation type="RESPONSE"><con:mediaType xsi:nil="true"/><con:status>204</con:status><con:params/><con:element>data</con:element></con:representation><con:representation type="RESPONSE"><con:mediaType xsi:nil="true"/><con:status>204</con:status><con:params/><con:element>data</con:element></con:representation><con:representation type="RESPONSE"><con:mediaType xsi:nil="true"/><con:status>204</con:status><con:params/><con:element>data</con:element></con:representation><con:representation type="RESPONSE"><con:mediaType xsi:nil="true"/><con:status>200</con:status><con:params/><con:element>data</con:element></con:representation><con:representation type="RESPONSE"><con:mediaType xsi:nil="true"/><con:status>204</con:status><con:params/><con:element>data</con:element></con:representation><con:representation type="RESPONSE"><con:mediaType xsi:nil="true"/><con:status>204</con:status><con:params/><con:element>data</con:element></con:representation><con:representation type="RESPONSE"><con:mediaType xsi:nil="true"/><con:status>204</con:status><con:params/><con:element>data</con:element></con:representation><con:representation type="RESPONSE"><con:mediaType xsi:nil="true"/><con:status>204</con:status><con:params/><con:element>data</con:element></con:representation><con:representation type="RESPONSE"><con:mediaType xsi:nil="true"/><con:status>204</con:status><con:params/><con:element>data</con:element></con:representation><con:representation type="RESPONSE"><con:mediaType xsi:nil="true"/><con:status>200</con:status><con:params/><con:element>data</con:element></con:representation><con:representation type="RESPONSE"><con:mediaType xsi:nil="true"/><con:status>204</con:status><con:params/><con:element>data</con:element></con:representation><con:representation type="RESPONSE"><con:mediaType xsi:nil="true"/><con:status>204</con:status><con:params/><con:element>data</con:element></con:representation><con:representation type="RESPONSE"><con:mediaType xsi:nil="true"/><con:status>200</con:status><con:params/><con:element>data</con:element></con:representation><con:representation type="RESPONSE"><con:mediaType xsi:nil="true"/><con:status>200</con:status><con:params/><con:element>data</con:element></con:representation><con:representation type="RESPONSE"><con:mediaType xsi:nil="true"/><con:status>200</con:status><con:params/><con:element>data</con:element></con:representation><con:representation type="RESPONSE"><con:mediaType xsi:nil="true"/><con:status>200</con:status><con:params/><con:element>data</con:element></con:representation><con:representation type="RESPONSE"><con:mediaType xsi:nil="true"/><con:status>200</con:status><con:params/><con:element>data</con:element></con:representation><con:request name="Student Delete" id="8e820f3b-ec65-432d-92a3-ddc499ad7f50" mediaType="application/json" postQueryString="false"><con:settings><con:setting id="com.eviware.soapui.impl.wsdl.WsdlRequest@request-headers">&lt;xml-fragment/></con:setting></con:settings><con:endpoint>http://localhost:8083</con:endpoint><con:request/><con:originalUri>http://localhost/student/8</con:originalUri><con:credentials><con:authType>No Authorization</con:authType></con:credentials><con:jmsConfig JMSDeliveryMode="PERSISTENT"/><con:jmsPropertyConfig/><con:parameters><entry key="id" value="-100" xmlns="http://eviware.com/soapui/config"/></con:parameters><con:parameterOrder><con:entry>id</con:entry></con:parameterOrder></con:request></con:method></con:resource></con:interface><con:testSuite id="74159805-f61b-4a4c-9239-2b44900bab1e" name="IT 21/18 Komosar Aleksa"><con:description>TestSuite generated for REST Service [http://localhost:8083]</con:description><con:settings/><con:runType>SEQUENTIAL</con:runType><con:testCase id="6c24db77-75f3-4fcc-9f4d-fb590ad2a6d0" failOnError="true" failTestCaseOnErrors="true" keepSession="false" maxResults="0" name="http://localhost:8083 TestSuite" searchProperties="true"><con:settings/><con:testStep type="restrequest" name="Projekat Get All" id="3657a884-d400-4090-b68a-c9b5b369547c"><con:settings/><con:config service="http://localhost:8083" resourcePath="/projekat" methodName="Method Get All" xsi:type="con:RestRequestStep" xmlns:xsi="http://www.w3.org/2001/XMLSchema-instance"><con:restRequest name="Projekat Get All" id="4c16f969-387c-4860-b7bb-cd174af638b8" mediaType="application/json" postQueryString="false"><con:settings><con:setting id="com.eviware.soapui.impl.wsdl.WsdlRequest@request-headers">&lt;xml-fragment/></con:setting></con:settings><con:endpoint>http://localhost:8083</con:endpoint><con:request/><con:originalUri>http://localhost/projekat</con:originalUri><con:assertion type="Valid HTTP Status Codes" id="ae16a6ad-bcfd-4d45-a5c1-3074606a33d0" name="Valid HTTP Status Codes"><con:configuration><codes>200</codes></con:configuration></con:assertion><con:credentials><con:authType>No Authorization</con:authType></con:credentials><con:jmsConfig JMSDeliveryMode="PERSISTENT"/><con:jmsPropertyConfig/><con:parameters/></con:restRequest></con:config></con:testStep><con:testStep type="restrequest" name="Projekat Get by ID" id="5b385e97-1993-4484-980b-25720b6f984e"><con:settings/><con:config service="http://localhost:8083" resourcePath="/projekat/{id}" methodName="Method Get by ID" xsi:type="con:RestRequestStep" xmlns:xsi="http://www.w3.org/2001/XMLSchema-instance"><con:restRequest name="Projekat Get by ID" id="b4e72bd2-6f09-4860-bbd0-5471e3fc2ee3" mediaType="application/json"><con:settings><con:setting id="com.eviware.soapui.impl.wsdl.WsdlRequest@request-headers">&lt;xml-fragment/></con:setting></con:settings><con:endpoint>http://localhost:8083</con:endpoint><con:request/><con:originalUri>http://localhost/projekat/</con:originalUri><con:assertion type="Valid HTTP Status Codes" id="a77d9524-391a-482f-bbb1-940d5cfde713" name="Valid HTTP Status Codes"><con:configuration><codes>200</codes></con:configuration></con:assertion><con:credentials><con:authType>No Authorization</con:authType></con:credentials><con:jmsConfig JMSDeliveryMode="PERSISTENT"/><con:jmsPropertyConfig/><con:parameters><entry key="id" value="-100" xmlns="http://eviware.com/soapui/config"/></con:parameters><con:parameterOrder><con:entry>id</con:entry></con:parameterOrder></con:restRequest></con:config></con:testStep><con:testStep type="restrequest" name="Projekat Get by Naziv" id="d8f1deb7-b37b-4fb3-b905-6c5bd280a65c"><con:settings/><con:config service="http://localhost:8083" resourcePath="/projekatNaziv/{naziv}" methodName="Method Get by Naziv" xsi:type="con:RestRequestStep" xmlns:xsi="http://www.w3.org/2001/XMLSchema-instance"><con:restRequest name="Projekat Get by Naziv" id="b1786c74-3686-4708-aae5-af83612c6b7c" mediaType="application/json"><con:settings><con:setting id="com.eviware.soapui.impl.wsdl.WsdlRequest@request-headers">&lt;xml-fragment/></con:setting></con:settings><con:endpoint>http://localhost:8083</con:endpoint><con:request/><con:originalUri>http://localhost/projekatNaziv/naziv</con:originalUri><con:assertion type="Valid HTTP Status Codes" id="95be36b8-6daa-43f3-880a-70fc85f54434" name="Valid HTTP Status Codes"><con:configuration><codes>200</codes></con:configuration></con:assertion><con:credentials><con:authType>No Authorization</con:authType></con:credentials><con:jmsConfig JMSDeliveryMode="PERSISTENT"/><con:jmsPropertyConfig/><con:parameters><entry key="naziv" value="mobi" xmlns="http://eviware.com/soapui/config"/></con:parameters></con:restRequest></con:config></con:testStep><con:testStep type="restrequest" name="Projekat Insert" id="3404fefb-a7fc-48a9-9b8f-f6dc01b7af28"><con:settings/><con:config service="http://localhost:8083" resourcePath="/projekat" methodName="Method Insert" xsi:type="con:RestRequestStep" xmlns:xsi="http://www.w3.org/2001/XMLSchema-instance"><con:restRequest name="Projekat Insert" id="37e5a2fe-bab2-46b6-9e31-b165a0aef57d" mediaType="application/json" postQueryString="false"><con:settings><con:setting id="com.eviware.soapui.impl.wsdl.WsdlRequest@request-headers">&lt;xml-fragment/></con:setting></con:settings><con:endpoint>http://localhost:8083</con:endpoint><con:request>{
      "id": -44,
      "naziv": "RVA - Studentska sluzba",
      "opis": "aOpis tehnologija..",
      "oznaka": "RVA"
}</con:request><con:originalUri>http://localhost/projekat</con:originalUri><con:assertion type="Valid HTTP Status Codes" id="ff5b303f-f2f2-4cf3-bfb5-e0e39e0d394f" name="Valid HTTP Status Codes"><con:configuration><codes>200</codes></con:configuration></con:assertion><con:credentials><con:authType>No Authorization</con:authType></con:credentials><con:jmsConfig JMSDeliveryMode="PERSISTENT"/><con:jmsPropertyConfig/><con:parameters/></con:restRequest></con:config></con:testStep><con:testStep type="restrequest" name="Projekat Update" id="12f36159-ad33-4fb5-b842-ba1df6081a8f"><con:settings/><con:config service="http://localhost:8083" resourcePath="/projekat" methodName="Method Update" xsi:type="con:RestRequestStep" xmlns:xsi="http://www.w3.org/2001/XMLSchema-instance"><con:restRequest name="Projekat Update" id="62034367-3707-42ad-9f59-2de14923040d" mediaType="application/json" postQueryString="false"><con:settings><con:setting id="com.eviware.soapui.impl.wsdl.WsdlRequest@request-headers">&lt;xml-fragment/></con:setting></con:settings><con:endpoint>http://localhost:8083</con:endpoint><con:request>      {
      "id": -100,
      "naziv": "RVAUpdate - Studentska sluzba",
      "opis": "Opis tehnologija..",
      "oznaka": "RVA2"
   }</con:request><con:originalUri>http://localhost/projekat</con:originalUri><con:assertion type="Valid HTTP Status Codes" id="d878181c-9124-4e7b-92c1-f525ddd0c91f" name="Valid HTTP Status Codes"><con:configuration><codes>200</codes></con:configuration></con:assertion><con:credentials><con:authType>No Authorization</con:authType></con:credentials><con:jmsConfig JMSDeliveryMode="PERSISTENT"/><con:jmsPropertyConfig/><con:parameters/></con:restRequest></con:config></con:testStep><con:testStep type="restrequest" name="Projekat Delete" id="98c75812-923f-4f53-8a11-aab0646a7c20"><con:settings/><con:config service="http://localhost:8083" resourcePath="/projekat/{id}" methodName="Method Delete" xsi:type="con:RestRequestStep" xmlns:xsi="http://www.w3.org/2001/XMLSchema-instance"><con:restRequest name="Projekat Delete" id="eb8e2262-a671-4e89-addb-48d6614acf14" mediaType="application/json" postQueryString="false"><con:settings><con:setting id="com.eviware.soapui.impl.wsdl.WsdlRequest@request-headers">&lt;xml-fragment/></con:setting></con:settings><con:endpoint>http://localhost:8083</con:endpoint><con:request/><con:originalUri>http://localhost/projekat/-46</con:originalUri><con:assertion type="Valid HTTP Status Codes" id="b92a2ee3-2734-4b44-96eb-b4de0e40b0f0" name="Valid HTTP Status Codes"><con:configuration><codes>200</codes></con:configuration></con:assertion><con:credentials><con:authType>No Authorization</con:authType></con:credentials><con:jmsConfig JMSDeliveryMode="PERSISTENT"/><con:jmsPropertyConfig/><con:parameters><entry key="id" value="-100" xmlns="http://eviware.com/soapui/config"/></con:parameters><con:parameterOrder><con:entry>id</con:entry></con:parameterOrder></con:restRequest></con:config></con:testStep><con:testStep type="restrequest" name="Smer Get All" id="b7a1cc70-c860-4c57-8a0e-639f55daaa01"><con:settings/><con:config service="http://localhost:8083" resourcePath="/smer" methodName="Method Get All" xsi:type="con:RestRequestStep" xmlns:xsi="http://www.w3.org/2001/XMLSchema-instance"><con:restRequest name="Smer Get All" id="fa044d17-0122-402e-ab59-66f504a0c3e7" mediaType="application/json"><con:settings><con:setting id="com.eviware.soapui.impl.wsdl.WsdlRequest@request-headers">&lt;xml-fragment/></con:setting></con:settings><con:endpoint>http://localhost:8083</con:endpoint><con:request/><con:originalUri>http://localhost/smer</con:originalUri><con:assertion type="Valid HTTP Status Codes" id="7c759558-1abd-4644-8725-516bb928d240" name="Valid HTTP Status Codes"><con:configuration><codes>200</codes></con:configuration></con:assertion><con:credentials><con:authType>No Authorization</con:authType></con:credentials><con:jmsConfig JMSDeliveryMode="PERSISTENT"/><con:jmsPropertyConfig/><con:parameters/></con:restRequest></con:config></con:testStep><con:testStep type="restrequest" name="Smer Get by ID" id="64424066-016a-4681-9138-fd1b110a0af4"><con:settings/><con:config service="http://localhost:8083" resourcePath="/smer/{id}" methodName="Method Get by ID" xsi:type="con:RestRequestStep" xmlns:xsi="http://www.w3.org/2001/XMLSchema-instance"><con:restRequest name="Smer Get by ID" id="92eedc3d-9945-45da-8cb2-a1eae14708b8" mediaType="application/json"><con:settings><con:setting id="com.eviware.soapui.impl.wsdl.WsdlRequest@request-headers">&lt;xml-fragment/></con:setting></con:settings><con:endpoint>http://localhost:8083</con:endpoint><con:request/><con:originalUri>http://localhost/smer/</con:originalUri><con:assertion type="Valid HTTP Status Codes" id="5bc6f999-5fb4-4760-93b3-77b8b8784848" name="Valid HTTP Status Codes"><con:configuration><codes>200</codes></con:configuration></con:assertion><con:credentials><con:authType>No Authorization</con:authType></con:credentials><con:jmsConfig JMSDeliveryMode="PERSISTENT"/><con:jmsPropertyConfig/><con:parameters><entry key="id" value="1" xmlns="http://eviware.com/soapui/config"/></con:parameters><con:parameterOrder><con:entry>id</con:entry></con:parameterOrder></con:restRequest></con:config></con:testStep><con:testStep type="restrequest" name="Smer Get by Naziv" id="f7f7c3d4-669b-4949-8832-5eeb0525c147"><con:settings/><con:config service="http://localhost:8083" resourcePath="/smerNaziv/{naziv}" methodName="Method Get by Naziv" xsi:type="con:RestRequestStep" xmlns:xsi="http://www.w3.org/2001/XMLSchema-instance"><con:restRequest name="Smer Get by Naziv" id="566a2042-bb0d-4efb-96de-99fd86d081e8" mediaType="application/json"><con:settings><con:setting id="com.eviware.soapui.impl.wsdl.WsdlRequest@request-headers">&lt;xml-fragment/></con:setting></con:settings><con:endpoint>http://localhost:8083</con:endpoint><con:request/><con:originalUri>http://localhost/smer/</con:originalUri><con:assertion type="Valid HTTP Status Codes" id="ad24c2d9-59ec-4efb-aff5-1c3bf517d08d" name="Valid HTTP Status Codes"><con:configuration><codes>200</codes></con:configuration></con:assertion><con:credentials><con:authType>No Authorization</con:authType></con:credentials><con:jmsConfig JMSDeliveryMode="PERSISTENT"/><con:jmsPropertyConfig/><con:parameters><entry key="naziv" value="i" xmlns="http://eviware.com/soapui/config"/></con:parameters><con:parameterOrder><con:entry>naziv</con:entry></con:parameterOrder></con:restRequest></con:config></con:testStep><con:testStep type="restrequest" name="Smer Insert" id="ba2db048-572b-4bee-b809-70a1b63e8071"><con:settings/><con:config service="http://localhost:8083" resourcePath="/smer" methodName="Method Insert" xsi:type="con:RestRequestStep" xmlns:xsi="http://www.w3.org/2001/XMLSchema-instance"><con:restRequest name="Smer Insert" id="f8a934cb-fccd-4a53-9a7e-99f40a4b4c2a" mediaType="application/json" postQueryString="false"><con:settings><con:setting id="com.eviware.soapui.impl.wsdl.WsdlRequest@request-headers">&lt;xml-fragment/></con:setting></con:settings><con:endpoint>http://localhost:8083</con:endpoint><con:request>      {
      "id": 35,
      "naziv": "aNovo Inzenjerstvo informacionih sistema",
      "oznaka": "aNovo IT"
   }</con:request><con:originalUri>http://localhost/smer</con:originalUri><con:assertion type="Valid HTTP Status Codes" id="2d2a545e-ae7c-41c3-ac06-188d3e687763" name="Valid HTTP Status Codes"><con:configuration><codes>200</codes></con:configuration></con:assertion><con:credentials><con:authType>No Authorization</con:authType></con:credentials><con:jmsConfig JMSDeliveryMode="PERSISTENT"/><con:jmsPropertyConfig/><con:parameters/></con:restRequest></con:config></con:testStep><con:testStep type="restrequest" name="Smer Update" id="e4fac9a1-070f-47e9-ba51-dc265d3cb669"><con:settings/><con:config service="http://localhost:8083" resourcePath="/smer" methodName="Method Update" xsi:type="con:RestRequestStep" xmlns:xsi="http://www.w3.org/2001/XMLSchema-instance"><con:restRequest name="Smer Update" id="7d5ddbc0-b31b-4d14-af46-d09aae2fdc2f" mediaType="application/json" postQueryString="false"><con:settings><con:setting id="com.eviware.soapui.impl.wsdl.WsdlRequest@request-headers">&lt;xml-fragment/></con:setting></con:settings><con:endpoint>http://localhost:8083</con:endpoint><con:request>      {
      "id": -100,
      "naziv": "UpdateNovo Inzenjerstvo informacionih sistema",
      "oznaka": "Update Novo IT"
   }</con:request><con:originalUri>http://localhost/smer</con:originalUri><con:assertion type="Valid HTTP Status Codes" id="27b80c8e-2448-4e68-baec-2575fbd90467" name="Valid HTTP Status Codes"><con:configuration><codes>200</codes></con:configuration></con:assertion><con:credentials><con:authType>No Authorization</con:authType></con:credentials><con:jmsConfig JMSDeliveryMode="PERSISTENT"/><con:jmsPropertyConfig/><con:parameters/></con:restRequest></con:config></con:testStep><con:testStep type="restrequest" name="Smer Delete" id="ea31f42f-7222-472d-bfea-f5005a09db41"><con:settings/><con:config service="http://localhost:8083" resourcePath="/smer/{id}" methodName="Method Delete" xsi:type="con:RestRequestStep" xmlns:xsi="http://www.w3.org/2001/XMLSchema-instance"><con:restRequest name="Smer Delete" id="36c3e142-8246-4f96-8e85-2125ed3241e4" mediaType="application/json" postQueryString="false"><con:settings><con:setting id="com.eviware.soapui.impl.wsdl.WsdlRequest@request-headers">&lt;xml-fragment/></con:setting></con:settings><con:endpoint>http://localhost:8083</con:endpoint><con:request/><con:originalUri>http://localhost/smer/-100</con:originalUri><con:assertion type="Valid HTTP Status Codes" id="6c3e7c5b-a85f-4481-a733-31dda09e00fb" name="Valid HTTP Status Codes"><con:configuration><codes>200</codes></con:configuration></con:assertion><con:credentials><con:authType>No Authorization</con:authType></con:credentials><con:jmsConfig JMSDeliveryMode="PERSISTENT"/><con:jmsPropertyConfig/><con:parameters><entry key="id" value="-100" xmlns="http://eviware.com/soapui/config"/></con:parameters><con:parameterOrder><con:entry>id</con:entry></con:parameterOrder></con:restRequest></con:config></con:testStep><con:testStep type="restrequest" name="Grupa Get All" id="91f3a4eb-42f8-4912-825f-b942d9cdef54"><con:settings/><con:config service="http://localhost:8083" resourcePath="/grupa" methodName="Method Get All" xsi:type="con:RestRequestStep" xmlns:xsi="http://www.w3.org/2001/XMLSchema-instance"><con:restRequest name="Grupa Get All" id="d3272ab3-3aa7-4bbf-a8c5-863d6d78423e" mediaType="application/json" postQueryString="false"><con:settings><con:setting id="com.eviware.soapui.impl.wsdl.WsdlRequest@request-headers">&lt;xml-fragment/></con:setting></con:settings><con:endpoint>http://localhost:8083</con:endpoint><con:request/><con:originalUri>http://localhost/grupa</con:originalUri><con:assertion type="Valid HTTP Status Codes" id="3d540e4e-28c1-4339-970c-f1143fd1f439" name="Valid HTTP Status Codes"><con:configuration><codes>200</codes></con:configuration></con:assertion><con:credentials><con:authType>No Authorization</con:authType></con:credentials><con:jmsConfig JMSDeliveryMode="PERSISTENT"/><con:jmsPropertyConfig/><con:parameters><entry key="id" value="" xmlns="http://eviware.com/soapui/config"/></con:parameters><con:parameterOrder><con:entry>id</con:entry></con:parameterOrder></con:restRequest></con:config></con:testStep><con:testStep type="restrequest" name="Grupa Get By ID" id="79de2310-a81d-43f3-9941-5ac37ca618c7"><con:settings/><con:config service="http://localhost:8083" resourcePath="/grupa/{id}" methodName="Method Get By ID" xsi:type="con:RestRequestStep" xmlns:xsi="http://www.w3.org/2001/XMLSchema-instance"><con:restRequest name="Grupa Get By ID" id="a5a03c45-09b1-4d4b-81f5-69a4d71b8c9a" mediaType="application/json"><con:settings><con:setting id="com.eviware.soapui.impl.wsdl.WsdlRequest@request-headers">&lt;xml-fragment/></con:setting></con:settings><con:endpoint>http://localhost:8083</con:endpoint><con:request/><con:originalUri>http://localhost/grupa/1</con:originalUri><con:assertion type="Valid HTTP Status Codes" id="2301daa9-e601-45c0-a783-56b519144e5d" name="Valid HTTP Status Codes"><con:configuration><codes>200</codes></con:configuration></con:assertion><con:credentials><con:authType>No Authorization</con:authType></con:credentials><con:jmsConfig JMSDeliveryMode="PERSISTENT"/><con:jmsPropertyConfig/><con:parameters><entry key="id" value="-100" xmlns="http://eviware.com/soapui/config"/></con:parameters><con:parameterOrder><con:entry>id</con:entry></con:parameterOrder></con:restRequest></con:config></con:testStep><con:testStep type="restrequest" name="Grupa Get By Oznaka" id="06c1a1ef-fa95-4675-b0fc-d5588a8f4be8"><con:settings/><con:config service="http://localhost:8083" resourcePath="/grupaOznaka/{oznaka}" methodName="Method Get By Oznaka" xsi:type="con:RestRequestStep" xmlns:xsi="http://www.w3.org/2001/XMLSchema-instance"><con:restRequest name="Grupa Get By Oznaka" id="3a8212ff-0839-4e71-80d4-ce7017fc63cc" mediaType="application/json"><con:settings><con:setting id="com.eviware.soapui.impl.wsdl.WsdlRequest@request-headers">&lt;xml-fragment/></con:setting></con:settings><con:endpoint>http://localhost:8083</con:endpoint><con:request/><con:originalUri>http://localhost/grupaOznaka/m</con:originalUri><con:assertion type="Valid HTTP Status Codes" id="6e9e52d7-c1fc-4c7b-b703-a3ad0d30ca88" name="Valid HTTP Status Codes"><con:configuration><codes>200</codes></con:configuration></con:assertion><con:credentials><con:authType>No Authorization</con:authType></con:credentials><con:jmsConfig JMSDeliveryMode="PERSISTENT"/><con:jmsPropertyConfig/><con:parameters><entry key="oznaka" value="III" xmlns="http://eviware.com/soapui/config"/></con:parameters><con:parameterOrder><con:entry>oznaka</con:entry></con:parameterOrder></con:restRequest></con:config></con:testStep><con:testStep type="restrequest" name="Grupa Insert" id="edb0ef78-b240-45f0-a632-d9ee019d11e3"><con:settings/><con:config service="http://localhost:8083" resourcePath="/grupa" methodName="Method Insert" xsi:type="con:RestRequestStep" xmlns:xsi="http://www.w3.org/2001/XMLSchema-instance"><con:restRequest name="Grupa Insert" id="acc80a41-6ccc-4763-88f0-a8fc65f49182" mediaType="application/json" postQueryString="false"><con:settings><con:setting id="com.eviware.soapui.impl.wsdl.WsdlRequest@request-headers">&lt;xml-fragment/></con:setting></con:settings><con:endpoint>http://localhost:8083</con:endpoint><con:request>      {
      "id": 38,
      "oznaka": "VI",
      "smer":       {
         "id": 4,
         "naziv": "Inzenjerski menadzment",
         "oznaka": "IM"
      }
      }</con:request><con:originalUri>http://localhost/grupa</con:originalUri><con:assertion type="Valid HTTP Status Codes" id="02cb0be8-ca64-4542-a1ff-5c89bc1c7fb6" name="Valid HTTP Status Codes"><con:configuration><codes>200</codes></con:configuration></con:assertion><con:credentials><con:authType>No Authorization</con:authType></con:credentials><con:jmsConfig JMSDeliveryMode="PERSISTENT"/><con:jmsPropertyConfig/><con:parameters/></con:restRequest></con:config></con:testStep><con:testStep type="restrequest" name="Grupa Update" id="f54e5db6-4702-4d20-b258-968446ad1cb9"><con:settings/><con:config service="http://localhost:8083" resourcePath="/grupa" methodName="Method Update" xsi:type="con:RestRequestStep" xmlns:xsi="http://www.w3.org/2001/XMLSchema-instance"><con:restRequest name="Grupa Update" id="59abd9d1-d851-4822-b6b7-a7a33d4275b9" mediaType="application/json" postQueryString="false"><con:settings><con:setting id="com.eviware.soapui.impl.wsdl.WsdlRequest@request-headers">&lt;xml-fragment/></con:setting></con:settings><con:endpoint>http://localhost:8083</con:endpoint><con:request>      {
      "id": -46,
      "oznaka": "II",
      "smer":       {
         "id": 2
      }
      }</con:request><con:originalUri>http://localhost/grupa</con:originalUri><con:assertion type="Valid HTTP Status Codes" id="bd1eb407-59dc-4d2e-bdbc-5d743471e9dd" name="Valid HTTP Status Codes"><con:configuration><codes>200</codes></con:configuration></con:assertion><con:credentials><con:authType>No Authorization</con:authType></con:credentials><con:jmsConfig JMSDeliveryMode="PERSISTENT"/><con:jmsPropertyConfig/><con:parameters/></con:restRequest></con:config></con:testStep><con:testStep type="restrequest" name="Grupa Delete" id="b2d365ce-c8f8-441c-8a0f-643593876f97"><con:settings/><con:config service="http://localhost:8083" resourcePath="/grupa/{id}" methodName="Method Delete" xsi:type="con:RestRequestStep" xmlns:xsi="http://www.w3.org/2001/XMLSchema-instance"><con:restRequest name="Grupa Delete" id="1f528f93-3e33-4e92-aff8-b4f56c9ff629" mediaType="application/json" postQueryString="false"><con:settings><con:setting id="com.eviware.soapui.impl.wsdl.WsdlRequest@request-headers">&lt;xml-fragment/></con:setting></con:settings><con:endpoint>http://localhost:8083</con:endpoint><con:request/><con:originalUri>http://localhost/grupa/</con:originalUri><con:assertion type="Valid HTTP Status Codes" id="3c9ddc9d-0630-49c2-88c6-235d4195df7c" name="Valid HTTP Status Codes"><con:configuration><codes>200</codes></con:configuration></con:assertion><con:credentials><con:authType>No Authorization</con:authType></con:credentials><con:jmsConfig JMSDeliveryMode="PERSISTENT"/><con:jmsPropertyConfig/><con:parameters><entry key="id" value="-100" xmlns="http://eviware.com/soapui/config"/></con:parameters><con:parameterOrder><con:entry>id</con:entry></con:parameterOrder></con:restRequest></con:config></con:testStep><con:testStep type="restrequest" name="Student Get All" id="872e08fa-46b7-4022-8fff-85448c3b4d82"><con:settings/><con:config service="http://localhost:8083" resourcePath="/student" methodName="Method Get All" xsi:type="con:RestRequestStep" xmlns:xsi="http://www.w3.org/2001/XMLSchema-instance"><con:restRequest name="Student Get All" id="8dea8085-26d6-40dd-a3b4-2c6d9ed47c7f" mediaType="application/json"><con:settings><con:setting id="com.eviware.soapui.impl.wsdl.WsdlRequest@request-headers">&lt;xml-fragment/></con:setting></con:settings><con:endpoint>http://localhost:8083</con:endpoint><con:request/><con:originalUri>http://localhost/student</con:originalUri><con:assertion type="Valid HTTP Status Codes" id="5f32d53c-04eb-4111-bfb8-7691e9d1190c" name="Valid HTTP Status Codes"><con:configuration><codes>200</codes></con:configuration></con:assertion><con:credentials><con:authType>No Authorization</con:authType></con:credentials><con:jmsConfig JMSDeliveryMode="PERSISTENT"/><con:jmsPropertyConfig/><con:parameters/></con:restRequest></con:config></con:testStep><con:testStep type="restrequest" name="Student Get By ID" id="d3059daa-d480-49ea-9e7c-5ca7de95bd9e"><con:settings/><con:config service="http://localhost:8083" resourcePath="/student/{id}" methodName="Method Get By ID" xsi:type="con:RestRequestStep" xmlns:xsi="http://www.w3.org/2001/XMLSchema-instance"><con:restRequest name="Student Get By ID" id="112a7476-782d-4132-9dea-190da243e466" mediaType="application/json"><con:settings><con:setting id="com.eviware.soapui.impl.wsdl.WsdlRequest@request-headers">&lt;xml-fragment/></con:setting></con:settings><con:endpoint>http://localhost:8083</con:endpoint><con:request/><con:originalUri>http://localhost/student/</con:originalUri><con:assertion type="Valid HTTP Status Codes" id="f4e080ed-b221-403e-9846-a18e263bbb83" name="Valid HTTP Status Codes"><con:configuration><codes>200</codes></con:configuration></con:assertion><con:credentials><con:authType>No Authorization</con:authType></con:credentials><con:jmsConfig JMSDeliveryMode="PERSISTENT"/><con:jmsPropertyConfig/><con:parameters/><con:parameterOrder><con:entry>id</con:entry></con:parameterOrder></con:restRequest></con:config></con:testStep><con:testStep type="restrequest" name="Student Get By Grupa" id="74042a81-7c07-45f7-b154-76ebcf6ce24e"><con:settings/><con:config service="http://localhost:8083" resourcePath="/studentGrupaID/{id}" methodName="Method Get By Grupa" xsi:type="con:RestRequestStep" xmlns:xsi="http://www.w3.org/2001/XMLSchema-instance"><con:restRequest name="Student Get By Grupa" id="8ce25536-f768-4037-ab41-fb5e4a7710bc" mediaType="application/json"><con:settings><con:setting id="com.eviware.soapui.impl.wsdl.WsdlRequest@request-headers">&lt;xml-fragment/></con:setting></con:settings><con:endpoint>http://localhost:8083</con:endpoint><con:request/><con:originalUri>http://localhost/studentGrupaID/</con:originalUri><con:assertion type="Valid HTTP Status Codes" id="efb06919-ff0c-491a-94aa-c5d8c919739c" name="Valid HTTP Status Codes"><con:configuration><codes>200</codes></con:configuration></con:assertion><con:credentials><con:authType>No Authorization</con:authType></con:credentials><con:jmsConfig JMSDeliveryMode="PERSISTENT"/><con:jmsPropertyConfig/><con:parameters><entry key="id" value="1" xmlns="http://eviware.com/soapui/config"/></con:parameters><con:parameterOrder><con:entry>id</con:entry></con:parameterOrder></con:restRequest></con:config></con:testStep><con:testStep type="restrequest" name="Student Get By ID Less" id="d9056d45-724a-4356-b0a3-49cdb7043ed4"><con:settings/><con:config service="http://localhost:8083" resourcePath="/studentPoId/{id}" methodName="Method Get By ID Less" xsi:type="con:RestRequestStep" xmlns:xsi="http://www.w3.org/2001/XMLSchema-instance"><con:restRequest name="Student Get By ID Less" id="1aa7ebad-51e2-492a-8c4b-5b16714fa776" mediaType="application/json"><con:settings><con:setting id="com.eviware.soapui.impl.wsdl.WsdlRequest@request-headers">&lt;xml-fragment/></con:setting></con:settings><con:endpoint>http://localhost:8083</con:endpoint><con:request/><con:originalUri>http://localhost/studentBrIndeksa/5</con:originalUri><con:assertion type="Valid HTTP Status Codes" id="09d8a039-b1ed-4a3a-9915-3280dfbaa7fe" name="Valid HTTP Status Codes"><con:configuration><codes>200</codes></con:configuration></con:assertion><con:credentials><con:authType>No Authorization</con:authType></con:credentials><con:jmsConfig JMSDeliveryMode="PERSISTENT"/><con:jmsPropertyConfig/><con:parameters><entry key="id" value="2" xmlns="http://eviware.com/soapui/config"/></con:parameters><con:parameterOrder><con:entry>id</con:entry></con:parameterOrder></con:restRequest></con:config></con:testStep><con:testStep type="restrequest" name="Student Insert" id="5b13fde6-50d3-4933-b65f-9d2ddd8ca274"><con:settings/><con:config service="http://localhost:8083" resourcePath="/student" methodName="Method Insert" xsi:type="con:RestRequestStep" xmlns:xsi="http://www.w3.org/2001/XMLSchema-instance"><con:restRequest name="Student Insert" id="3af35aa9-2853-49f5-8f4a-888f857b7f19" mediaType="application/json" postQueryString="false"><con:settings><con:setting id="com.eviware.soapui.impl.wsdl.WsdlRequest@request-headers">&lt;xml-fragment/></con:setting></con:settings><con:endpoint>http://localhost:8083</con:endpoint><con:request>{
   "id": 8,
   "brojIndeksa": "IzmenaAAATest21/2018",
   "ime": "TestAleksa",
   "prezime": "TestKomosar",
   "grupa":    {
      "id": 1,
      "oznaka": "II",
      "smer":       {
         "id": 1,
         "naziv": "Inzenjerstvo informacionih sistema",
         "oznaka": "IT"
      }
   },
   "projekat":    {
      "id": 4,
      "naziv": "Naucna konferencija",
      "opis": "Kreiranje baze podata IS Naucne konferencije FTN-a. Pored razumevanja procesa organizovanja dogadja, potrebno je izraditi semu cele baze podataka, ogranicenja, kao i relacionu semu BP.",
      "oznaka": "PBP"
   }
}</con:request><con:originalUri>http://localhost/student</con:originalUri><con:assertion type="Valid HTTP Status Codes" id="2066d98c-5db4-4274-8558-8430e31a2254" name="Valid HTTP Status Codes"><con:configuration><codes>200</codes></con:configuration></con:assertion><con:credentials><con:authType>No Authorization</con:authType></con:credentials><con:jmsConfig JMSDeliveryMode="PERSISTENT"/><con:jmsPropertyConfig/><con:parameters/></con:restRequest></con:config></con:testStep><con:testStep type="restrequest" name="Student Update" id="ca852270-46f8-4606-a07b-5da8c7807e80"><con:settings/><con:config service="http://localhost:8083" resourcePath="/student" methodName="Method Update" xsi:type="con:RestRequestStep" xmlns:xsi="http://www.w3.org/2001/XMLSchema-instance"><con:restRequest name="Student Update" id="f3c966bb-36a7-46e0-aa52-259ec90400f5" mediaType="application/json" postQueryString="false"><con:settings><con:setting id="com.eviware.soapui.impl.wsdl.WsdlRequest@request-headers">&lt;xml-fragment/></con:setting></con:settings><con:endpoint>http://localhost:8083</con:endpoint><con:request>{
   "id": 2,
   "brojIndeksa": "IzmenaAAATest21/2018",
   "ime": "TestAleksa",
   "prezime": "TestKomosar",
   "grupa":    {
      "id": 1,
      "oznaka": "II",
      "smer":       {
         "id": 1,
         "naziv": "Inzenjerstvo informacionih sistema",
         "oznaka": "IT"
      }
   },
   "projekat":    {
      "id": 4,
      "naziv": "Naucna konferencija",
      "opis": "Kreiranje baze podata IS Naucne konferencije FTN-a. Pored razumevanja procesa organizovanja dogadja, potrebno je izraditi semu cele baze podataka, ogranicenja, kao i relacionu semu BP.",
      "oznaka": "PBP"
   }
}</con:request><con:originalUri>http://localhost/student</con:originalUri><con:assertion type="Valid HTTP Status Codes" id="1ba31b7b-25c2-4071-85f0-f269b40afd84" name="Valid HTTP Status Codes"><con:configuration><codes>200</codes></con:configuration></con:assertion><con:credentials><con:authType>No Authorization</con:authType></con:credentials><con:jmsConfig JMSDeliveryMode="PERSISTENT"/><con:jmsPropertyConfig/><con:parameters/></con:restRequest></con:config></con:testStep><con:testStep type="restrequest" name="Student Delete" id="52cd5ceb-f6c8-4c62-9ccf-2c6149a0952e"><con:settings/><con:config service="http://localhost:8083" resourcePath="/student/{id}" methodName="Method Delete" xsi:type="con:RestRequestStep" xmlns:xsi="http://www.w3.org/2001/XMLSchema-instance"><con:restRequest name="Student Delete" id="8e820f3b-ec65-432d-92a3-ddc499ad7f50" mediaType="application/json" postQueryString="false"><con:settings><con:setting id="com.eviware.soapui.impl.wsdl.WsdlRequest@request-headers">&lt;xml-fragment/></con:setting></con:settings><con:endpoint>http://localhost:8083</con:endpoint><con:request/><con:originalUri>http://localhost/student/8</con:originalUri><con:assertion type="Valid HTTP Status Codes" id="6857f85f-e80f-45c6-a217-7ce6a82890d2" name="Valid HTTP Status Codes"><con:configuration><codes>200</codes></con:configuration></con:assertion><con:credentials><con:authType>No Authorization</con:authType></con:credentials><con:jmsConfig JMSDeliveryMode="PERSISTENT"/><con:jmsPropertyConfig/><con:parameters><entry key="id" value="-100" xmlns="http://eviware.com/soapui/config"/></con:parameters><con:parameterOrder><con:entry>id</con:entry></con:parameterOrder></con:restRequest></con:config></con:testStep><con:properties/></con:testCase><con:properties/></con:testSuite><con:properties/><con:wssContainer/><con:oAuth2ProfileContainer/><con:oAuth1ProfileContainer/><con:sensitiveInformation/></con:soapui-project>